wecon_sqlalchemy/__init__.pyc
wecon_sqlalchemy/events.pyc
wecon_sqlalchemy/exc.pyc
wecon_sqlalchemy/inspection.pyc
wecon_sqlalchemy/log.pyc
wecon_sqlalchemy/py.typed
wecon_sqlalchemy/schema.pyc
wecon_sqlalchemy/types.pyc
wecon_sqlalchemy/connectors/__init__.pyc
wecon_sqlalchemy/connectors/aioodbc.pyc
wecon_sqlalchemy/connectors/asyncio.pyc
wecon_sqlalchemy/connectors/pyodbc.pyc
wecon_sqlalchemy/cyextension/__init__.pyc
wecon_sqlalchemy/cyextension/collections.cpython-313t-arm-linux-gnueabihf.so
wecon_sqlalchemy/cyextension/collections.pyx
wecon_sqlalchemy/cyextension/immutabledict.cpython-313t-arm-linux-gnueabihf.so
wecon_sqlalchemy/cyextension/immutabledict.pxd
wecon_sqlalchemy/cyextension/immutabledict.pyx
wecon_sqlalchemy/cyextension/processors.cpython-313t-arm-linux-gnueabihf.so
wecon_sqlalchemy/cyextension/processors.pyx
wecon_sqlalchemy/cyextension/resultproxy.cpython-313t-arm-linux-gnueabihf.so
wecon_sqlalchemy/cyextension/resultproxy.pyx
wecon_sqlalchemy/cyextension/util.cpython-313t-arm-linux-gnueabihf.so
wecon_sqlalchemy/cyextension/util.pyx
wecon_sqlalchemy/dialects/__init__.pyc
wecon_sqlalchemy/dialects/_typing.pyc
wecon_sqlalchemy/dialects/type_migration_guidelines.txt
wecon_sqlalchemy/dialects/mssql/__init__.pyc
wecon_sqlalchemy/dialects/mssql/aioodbc.pyc
wecon_sqlalchemy/dialects/mssql/base.pyc
wecon_sqlalchemy/dialects/mssql/information_schema.pyc
wecon_sqlalchemy/dialects/mssql/json.pyc
wecon_sqlalchemy/dialects/mssql/provision.pyc
wecon_sqlalchemy/dialects/mssql/pymssql.pyc
wecon_sqlalchemy/dialects/mssql/pyodbc.pyc
wecon_sqlalchemy/dialects/mysql/__init__.pyc
wecon_sqlalchemy/dialects/mysql/aiomysql.pyc
wecon_sqlalchemy/dialects/mysql/asyncmy.pyc
wecon_sqlalchemy/dialects/mysql/base.pyc
wecon_sqlalchemy/dialects/mysql/cymysql.pyc
wecon_sqlalchemy/dialects/mysql/dml.pyc
wecon_sqlalchemy/dialects/mysql/enumerated.pyc
wecon_sqlalchemy/dialects/mysql/expression.pyc
wecon_sqlalchemy/dialects/mysql/json.pyc
wecon_sqlalchemy/dialects/mysql/mariadb.pyc
wecon_sqlalchemy-2.0.41.dist-info/METADATA
wecon_sqlalchemy-2.0.41.dist-info/WHEEL
wecon_sqlalchemy-2.0.41.dist-info/top_level.txt
wecon_sqlalchemy-2.0.41.dist-info/RECORD
