Metadata-Version: 2.1
Name: wecon_sqlalchemy
Version: 2.0.41
Summary: Auto-generated package for wecon_sqlalchemy
Home-page: UNKNOWN
Author: WECON_HJB
License: UNKNOWN
Platform: linux-armv7l
Requires-Python: >=3.9
